datamart_yhdr/__init__.py
datamart_yhdr/const.py
datamart_yhdr/interface.py
datamart_yhdr/settings.py
datamart_yhdr-0.1.8.dist-info/METADATA
datamart_yhdr-0.1.8.dist-info/WHEEL
datamart_yhdr-0.1.8.dist-info/licenses/LICENSE
datamart_yhdr-0.1.8.dist-info/RECORD
